Metadata-Version: 2.4
Name: lpce
Version: 0.1.0
Summary: Ligand-protein complex extraction
Requires-Python: >=3.11
Requires-Dist: biopython>=1.85
Requires-Dist: build>=1.2.2.post1
Requires-Dist: hydra-core>=1.3.2
Requires-Dist: joblib>=1.4.2
Requires-Dist: loguru>=0.7.3
Requires-Dist: pre-commit>=4.2.0
Requires-Dist: pytest>=8.3.5
Requires-Dist: tqdm>=4.67.1
Requires-Dist: twine>=6.1.0
Requires-Dist: yagmail>=0.15.293
